{"tipo_veiculo":"carro","marca":"Chevrolet","modelo":"Camaro","ano":"2015","valor":"R$ 246.999,00","descricao":"O Camaro 2015 é um ícone de design e desempenho da Chevrolet, que combina a potência de um clássico muscle car com tecnologias modernas. Equipado com um motor V8 de 6.2 litros, ele entrega cerca de 406 cavalos de potência e um torque impressionante, proporcionando acelerações rápidas e uma experiência de condução empolgante. \r\n\r\nO design exterior destaca linhas agressivas e aerodinâmicas, com uma frente imponente e faróis afilados. Internamente, oferece uma cabine confortável com materiais de qualidade, além de recursos tecnológicos como tela sensível ao toque, sistema de som premium e conectividade Bluetooth. O Camaro 2015 é ideal para quem busca potência e estilo em um só veículo.","troca":"Não","pecas":"Apenas veículo completo","rodas":"Não","telefone":"(47) 0000-0000","hodometro":"156.398 km","estado":"SC","cidade":"Joinville","bairro":"Boa Vista","estetica":"Impecável","mecanica":"Quase perfeita","quantidade_donos":"Apenas 1 dono","condicao_rodas":"Semi-Novos","tipo_rodas":"Liga leve","tamanho_rodas":"20''"}